pysimultan_jinja/__about__.py
pysimultan_jinja/__init__.py
pysimultan_jinja/contents.py
pysimultan_jinja/main.py
pysimultan_jinja/mapper.py
pysimultan_jinja/maps.py
pysimultan_jinja/method_mapper.py
pysimultan_jinja/view_manager.py
pysimultan_jinja/core/JinjaTemplate.py
pysimultan_jinja/core/__init__.py
pysimultan_jinja/core/example.py
pysimultan_jinja-1.0.0.dist-info/METADATA
pysimultan_jinja-1.0.0.dist-info/WHEEL
pysimultan_jinja-1.0.0.dist-info/licenses/LICENSE.txt
pysimultan_jinja-1.0.0.dist-info/RECORD
